hydrobench/__init__.py
hydrobench/blind.py
hydrobench/client.py
hydrobench-0.1.1.dist-info/METADATA
hydrobench-0.1.1.dist-info/WHEEL
hydrobench-0.1.1.dist-info/top_level.txt
hydrobench-0.1.1.dist-info/RECORD
