Metadata-Version: 2.4
Name: hydrobench
Version: 0.1.1
Summary: Hydrological benchmarking toolkit
Author-email: Mirko Mälicke <mirko@hydrocode.de>
Requires-Python: >=3.10
Requires-Dist: pocketbase
Requires-Dist: polars>=1.37.1
